pytemperatureconverter/__init__.py
pytemperatureconverter/functions.py
pytemperatureconverter-1.2.0.dist-info/LICENSE
pytemperatureconverter-1.2.0.dist-info/METADATA
pytemperatureconverter-1.2.0.dist-info/WHEEL
pytemperatureconverter-1.2.0.dist-info/top_level.txt
pytemperatureconverter-1.2.0.dist-info/RECORD
