Metadata-Version: 2.1
Name: pytemperatureconverter
Version: 1.2.0
Summary: A simple Python library to convert temperatures between four scales (Celsius, Fahrenheit, Kelvin, and Rankine) with warnings for physically impossible conversions.
Home-page: https://github.com/manxlr
Author: Zeeshan Khalid
Author-email: nszeeshankhalid@gmail.com
Classifier: Programming Language :: Python :: 3
Classifier: License :: OSI Approved :: MIT License
Classifier: Operating System :: OS Independent
Requires-Python: >=3.6
License-File: LICENSE
